davidkhala/google/maps/__init__.py
davidkhala/google/maps/place.py
davidkhala_google_maps-0.0.0.dist-info/METADATA
davidkhala_google_maps-0.0.0.dist-info/WHEEL
davidkhala_google_maps-0.0.0.dist-info/RECORD
