Metadata-Version: 2.4
Name: davidkhala.google.maps
Version: 0.0.0
Summary: Add your description here
Requires-Python: >=3.12
Requires-Dist: google-maps-places
